_wenet.cpython-38-darwin.so
libwenet_api.dylib
wenetruntime/decoder.py
wenetruntime/__init__.py
wenetruntime/hub.py
wenetruntime/main.py
wenetruntime/__main__.py
wenetruntime/.dylibs/libtorch.dylib
wenetruntime/.dylibs/libiomp5.dylib
wenetruntime/.dylibs/libtorch_cpu.dylib
wenetruntime/.dylibs/libc10.dylib
wenetruntime/.dylibs/libwenet_api.dylib
wenetruntime-1.14.0.dist-info/RECORD
wenetruntime-1.14.0.dist-info/WHEEL
wenetruntime-1.14.0.dist-info/entry_points.txt
wenetruntime-1.14.0.dist-info/top_level.txt
wenetruntime-1.14.0.dist-info/METADATA
