Metadata-Version: 2.1
Name: wenetruntime
Version: 1.14.0
Home-page: https://github.com/wenet-e2e/wenet
Author: Binbin Zhang
Author-email: binbzha@qq.com
License: Apache licensed, as found in the LICENSE file
Classifier: Programming Language :: C++
Classifier: Programming Language :: Python :: 3
Classifier: Operating System :: OS Independent
Classifier: Topic :: Scientific/Engineering :: Artificial Intelligence
Requires-Dist: torch (>=1.10.0)
Requires-Dist: librosa
Requires-Dist: tqdm
